{
  "summary": {
    "title": "Cybersecurity Assignment 1",
    "owner": "Bridget Le"
  },
  "detail": {
    "contributors": [],
    "diagrams": [
      {
        "title": "Threat Model - PrimeTech",
        "thumbnail": "./public/content/images/thumbnail.jpg",
        "id": 0,
        "diagramJson": {
          "cells": [
            {
              "type": "tm.Process",
              "size": {
                "width": 100,
                "height": 100
              },
              "position": {
                "x": 779,
                "y": 287
              },
              "angle": 0,
              "id": "8aa6e2f9-ea6a-4cc2-b8f6-2997c8c2b125",
              "z": 1,
              "hasOpenThreats": false,
              "attrs": {
                ".element-shape": {
                  "class": "element-shape hasNoOpenThreats isInScope"
                },
                "text": {
                  "text": "Web\nApplication\n(Angular 4)"
                },
                ".element-text": {
                  "class": "element-text hasNoOpenThreats isInScope"
                }
              }
            },
            {
              "type": "tm.Process",
              "size": {
                "width": 100,
                "height": 100
              },
              "position": {
                "x": 782,
                "y": 568
              },
              "angle": 0,
              "id": "d5358155-20c4-42b0-b202-7aa9fe71c391",
              "z": 2,
              "hasOpenThreats": false,
              "attrs": {
                ".element-shape": {
                  "class": "element-shape hasNoOpenThreats isInScope"
                },
                "text": {
                  "text": "RESTful API\n(PHP)"
                },
                ".element-text": {
                  "class": "element-text hasNoOpenThreats isInScope"
                }
              }
            },
            {
              "type": "tm.Actor",
              "size": {
                "width": 160,
                "height": 80
              },
              "position": {
                "x": 200,
                "y": 139
              },
              "angle": 0,
              "id": "de96ef9e-0bd9-405a-aaa2-e4ad09d05cce",
              "z": 3,
              "hasOpenThreats": false,
              "attrs": {
                ".element-shape": {
                  "class": "element-shape hasNoOpenThreats isInScope"
                },
                "text": {
                  "text": "User/Browser"
                },
                ".element-text": {
                  "class": "element-text hasNoOpenThreats isInScope"
                }
              }
            },
            {
              "type": "tm.Store",
              "size": {
                "width": 160,
                "height": 80
              },
              "position": {
                "x": 753,
                "y": 797
              },
              "angle": 0,
              "id": "5eb0c940-6b7d-43af-b15b-47965536b7cd",
              "z": 4,
              "hasOpenThreats": false,
              "attrs": {
                ".element-shape": {
                  "class": "element-shape hasNoOpenThreats isInScope"
                },
                "text": {
                  "text": "Database (MYSQL)"
                },
                ".element-text": {
                  "class": "element-text hasNoOpenThreats isInScope"
                }
              }
            },
            {
              "type": "tm.Store",
              "size": {
                "width": 160,
                "height": 80
              },
              "position": {
                "x": 1148,
                "y": 450
              },
              "angle": 0,
              "id": "5364753a-496f-461e-bc05-42551c10a24d",
              "z": 5,
              "hasOpenThreats": false,
              "attrs": {
                ".element-shape": {
                  "class": "element-shape hasNoOpenThreats isInScope"
                },
                "text": {
                  "text": "Logs"
                },
                ".element-text": {
                  "class": "element-text hasNoOpenThreats isInScope"
                }
              }
            },
            {
              "type": "tm.Actor",
              "size": {
                "width": 160,
                "height": 80
              },
              "position": {
                "x": 451,
                "y": 883
              },
              "angle": 0,
              "id": "7611af7c-c1d5-45f7-a4cb-88bb9755bfcb",
              "z": 6,
              "hasOpenThreats": false,
              "attrs": {
                ".element-shape": {
                  "class": "element-shape hasNoOpenThreats isInScope"
                },
                "text": {
                  "text": "DB Client"
                },
                ".element-text": {
                  "class": "element-text hasNoOpenThreats isInScope"
                }
              }
            },
            {
              "type": "tm.Actor",
              "size": {
                "width": 160,
                "height": 80
              },
              "position": {
                "x": 144,
                "y": 334
              },
              "angle": 0,
              "id": "3d045863-4b5b-4a23-88f3-dc4ab47cb406",
              "z": 7,
              "hasOpenThreats": false,
              "attrs": {
                ".element-shape": {
                  "class": "element-shape hasNoOpenThreats isInScope"
                },
                "text": {
                  "text": "Mobile Application\n(React Native)"
                },
                ".element-text": {
                  "class": "element-text hasNoOpenThreats isInScope"
                }
              }
            },
            {
              "type": "tm.Store",
              "size": {
                "width": 160,
                "height": 80
              },
              "position": {
                "x": 675,
                "y": 1055
              },
              "angle": 0,
              "id": "78e2d891-873e-4ff9-b295-5313ec27d33c",
              "z": 8,
              "hasOpenThreats": false,
              "attrs": {
                ".element-shape": {
                  "class": "element-shape hasNoOpenThreats isInScope"
                },
                "text": {
                  "text": "DB Logs"
                },
                ".element-text": {
                  "class": "element-text hasNoOpenThreats isInScope"
                }
              }
            },
            {
              "type": "tm.Flow",
              "smooth": true,
              "source": {
                "id": "d5424603-0c19-40a4-82f4-04cd0f1f5388"
              },
              "target": {
                "id": "de96ef9e-0bd9-405a-aaa2-e4ad09d05cce"
              },
              "vertices": [
                {
                  "x": 478,
                  "y": 183
                }
              ],
              "id": "997843ff-b6e2-4d94-8b7f-c854f58f0762",
              "labels": [
                {
                  "position": {
                    "distance": 0.524470672058094,
                    "offset": 20.03475887182186
                  },
                  "attrs": {
                    "text": {
                      "text": "Web Response",
                      "font-weight": "400",
                      "font-size": "small"
                    }
                  }
                }
              ],
              "z": 9,
              "hasOpenThreats": false,
              "attrs": {
                ".marker-target": {
                  "class": "marker-target hasNoOpenThreats isInScope"
                },
                ".connection": {
                  "class": "connection hasNoOpenThreats isInScope"
                }
              }
            },
            {
              "type": "tm.Flow",
              "smooth": true,
              "source": {
                "id": "de96ef9e-0bd9-405a-aaa2-e4ad09d05cce"
              },
              "target": {
                "id": "d5424603-0c19-40a4-82f4-04cd0f1f5388"
              },
              "vertices": [
                {
                  "x": 444,
                  "y": 295
                }
              ],
              "id": "397ab63a-98a0-4ce4-ad44-e37c7909fb5c",
              "labels": [
                {
                  "position": {
                    "distance": 0.4706435203552246,
                    "offset": 22
                  },
                  "attrs": {
                    "text": {
                      "text": "Web Request",
                      "font-weight": "400",
                      "font-size": "small"
                    }
                  }
                }
              ],
              "z": 10,
              "hasOpenThreats": false,
              "attrs": {
                ".marker-target": {
                  "class": "marker-target hasNoOpenThreats isInScope"
                },
                ".connection": {
                  "class": "connection hasNoOpenThreats isInScope"
                }
              }
            },
            {
              "type": "tm.Flow",
              "smooth": true,
              "source": {
                "id": "d5358155-20c4-42b0-b202-7aa9fe71c391"
              },
              "target": {
                "id": "5eb0c940-6b7d-43af-b15b-47965536b7cd"
              },
              "vertices": [
                {
                  "x": 871,
                  "y": 727
                }
              ],
              "id": "273cd363-121d-4e65-a080-b2a9d650a348",
              "labels": [
                {
                  "position": {
                    "distance": 0.48088517341322057,
                    "offset": -15.077426703387772
                  },
                  "attrs": {
                    "text": {
                      "text": "DB Queries",
                      "font-weight": "400",
                      "font-size": "small"
                    }
                  }
                }
              ],
              "z": 11,
              "hasOpenThreats": false,
              "attrs": {
                ".marker-target": {
                  "class": "marker-target hasNoOpenThreats isInScope"
                },
                ".connection": {
                  "class": "connection hasNoOpenThreats isInScope"
                }
              }
            },
            {
              "type": "tm.Flow",
              "smooth": true,
              "source": {
                "x": 844,
                "y": 569
              },
              "target": {
                "id": "8aa6e2f9-ea6a-4cc2-b8f6-2997c8c2b125"
              },
              "vertices": [
                {
                  "x": 866,
                  "y": 469
                }
              ],
              "id": "7a3ca1ea-3bf8-46bb-afad-59bb94c01d87",
              "labels": [
                {
                  "position": 0.5,
                  "attrs": {
                    "text": {
                      "text": "flow 11",
                      "font-weight": "400",
                      "font-size": "small"
                    }
                  }
                }
              ],
              "z": 12,
              "hasOpenThreats": false,
              "attrs": {
                ".marker-target": {
                  "class": "marker-target hasNoOpenThreats isInScope"
                },
                ".connection": {
                  "class": "connection hasNoOpenThreats isInScope"
                }
              }
            },
            {
              "type": "tm.Flow",
              "smooth": true,
              "source": {
                "id": "8aa6e2f9-ea6a-4cc2-b8f6-2997c8c2b125"
              },
              "target": {
                "x": 814,
                "y": 567
              },
              "vertices": [
                {
                  "x": 775,
                  "y": 476
                }
              ],
              "id": "15fc9fae-0c88-4240-aa4b-77745df42794",
              "labels": [
                {
                  "position": {
                    "distance": 0.5068992719255514,
                    "offset": 0.039021634888194955
                  },
                  "attrs": {
                    "text": {
                      "text": "flow 12",
                      "font-weight": "400",
                      "font-size": "small"
                    }
                  }
                }
              ],
              "z": 13,
              "hasOpenThreats": false,
              "attrs": {
                ".marker-target": {
                  "class": "marker-target hasNoOpenThreats isInScope"
                },
                ".connection": {
                  "class": "connection hasNoOpenThreats isInScope"
                }
              }
            },
            {
              "type": "tm.Flow",
              "smooth": true,
              "source": {
                "id": "5eb0c940-6b7d-43af-b15b-47965536b7cd"
              },
              "target": {
                "x": 798,
                "y": 661
              },
              "vertices": [
                {
                  "x": 784,
                  "y": 730
                }
              ],
              "id": "188c6a1c-686d-4e09-b0ee-96ba053b1469",
              "labels": [
                {
                  "position": {
                    "distance": 0.5261719113413773,
                    "offset": -29.835129561393735
                  },
                  "attrs": {
                    "text": {
                      "text": "DB Query Results",
                      "font-weight": "400",
                      "font-size": "small"
                    }
                  }
                }
              ],
              "z": 14,
              "hasOpenThreats": false,
              "attrs": {
                ".marker-target": {
                  "class": "marker-target hasNoOpenThreats isInScope"
                },
                ".connection": {
                  "class": "connection hasNoOpenThreats isInScope"
                }
              }
            },
            {
              "type": "tm.Flow",
              "smooth": true,
              "source": {
                "x": 781,
                "y": 603
              },
              "target": {
                "id": "3d045863-4b5b-4a23-88f3-dc4ab47cb406"
              },
              "vertices": [
                {
                  "x": 664,
                  "y": 473
                }
              ],
              "id": "8ec1644f-4086-4d8b-89ff-7bf979a58db0",
              "labels": [
                {
                  "position": {
                    "distance": 0.5324057221882708,
                    "offset": 19.03813941589471
                  },
                  "attrs": {
                    "text": {
                      "text": "API Response",
                      "font-weight": "400",
                      "font-size": "small"
                    }
                  }
                }
              ],
              "z": 15,
              "hasOpenThreats": false,
              "attrs": {
                ".marker-target": {
                  "class": "marker-target hasNoOpenThreats isInScope"
                },
                ".connection": {
                  "class": "connection hasNoOpenThreats isInScope"
                }
              }
            },
            {
              "type": "tm.Flow",
              "smooth": true,
              "source": {
                "id": "3d045863-4b5b-4a23-88f3-dc4ab47cb406"
              },
              "target": {
                "x": 779,
                "y": 628
              },
              "vertices": [
                {
                  "x": 630,
                  "y": 515
                }
              ],
              "id": "533d6879-38f5-4fe9-a836-7545c1cd873f",
              "labels": [
                {
                  "position": {
                    "distance": 0.488429732223423,
                    "offset": 20.891809948921832
                  },
                  "attrs": {
                    "text": {
                      "text": "API Request",
                      "font-weight": "400",
                      "font-size": "small"
                    }
                  }
                }
              ],
              "z": 16,
              "hasOpenThreats": false,
              "attrs": {
                ".marker-target": {
                  "class": "marker-target hasNoOpenThreats isInScope"
                },
                ".connection": {
                  "class": "connection hasNoOpenThreats isInScope"
                }
              }
            },
            {
              "type": "tm.Flow",
              "smooth": true,
              "source": {
                "id": "d5358155-20c4-42b0-b202-7aa9fe71c391"
              },
              "target": {
                "id": "5364753a-496f-461e-bc05-42551c10a24d"
              },
              "vertices": [
                {
                  "x": 1016,
                  "y": 493
                }
              ],
              "id": "43e7d184-fbc6-4313-afeb-eedb14d7fe95",
              "labels": [
                {
                  "position": {
                    "distance": 0.46230088608103964,
                    "offset": -28.01512752479131
                  },
                  "attrs": {
                    "text": {
                      "text": "Write Log",
                      "font-weight": "400",
                      "font-size": "small"
                    }
                  }
                }
              ],
              "z": 17,
              "hasOpenThreats": false,
              "attrs": {
                ".marker-target": {
                  "class": "marker-target hasNoOpenThreats isInScope"
                },
                ".connection": {
                  "class": "connection hasNoOpenThreats isInScope"
                }
              }
            },
            {
              "type": "tm.Flow",
              "smooth": true,
              "source": {
                "x": 615,
                "y": 916
              },
              "target": {
                "id": "5eb0c940-6b7d-43af-b15b-47965536b7cd"
              },
              "vertices": [
                {
                  "x": 669,
                  "y": 833
                }
              ],
              "id": "ccc5086c-6473-4fb6-96bd-5b24a2891295",
              "labels": [
                {
                  "position": {
                    "distance": 0.43657001355133596,
                    "offset": -32.29405454761226
                  },
                  "attrs": {
                    "text": {
                      "text": "flow 17",
                      "font-weight": "400",
                      "font-size": "small"
                    }
                  }
                }
              ],
              "z": 18,
              "hasOpenThreats": false,
              "attrs": {
                ".marker-target": {
                  "class": "marker-target hasNoOpenThreats isInScope"
                },
                ".connection": {
                  "class": "connection hasNoOpenThreats isInScope"
                }
              }
            },
            {
              "type": "tm.Flow",
              "smooth": true,
              "source": {
                "id": "5eb0c940-6b7d-43af-b15b-47965536b7cd"
              },
              "target": {
                "id": "7611af7c-c1d5-45f7-a4cb-88bb9755bfcb"
              },
              "vertices": [
                {
                  "x": 710,
                  "y": 948
                }
              ],
              "id": "c417c331-0a15-4f93-b444-4b665a0c1bca",
              "labels": [
                {
                  "position": {
                    "distance": 0.5380388785671605,
                    "offset": -32.19428107471391
                  },
                  "attrs": {
                    "text": {
                      "text": "flow 18",
                      "font-weight": "400",
                      "font-size": "small"
                    }
                  }
                }
              ],
              "z": 19,
              "hasOpenThreats": false,
              "attrs": {
                ".marker-target": {
                  "class": "marker-target hasNoOpenThreats isInScope"
                },
                ".connection": {
                  "class": "connection hasNoOpenThreats isInScope"
                }
              }
            },
            {
              "type": "tm.Flow",
              "smooth": true,
              "source": {
                "id": "5eb0c940-6b7d-43af-b15b-47965536b7cd"
              },
              "target": {
                "id": "78e2d891-873e-4ff9-b295-5313ec27d33c"
              },
              "vertices": [],
              "id": "90249853-3f21-4dd4-9955-2ac9a97fa5b7",
              "labels": [
                {
                  "position": 0.5,
                  "attrs": {
                    "text": {
                      "text": "flow 19",
                      "font-weight": "400",
                      "font-size": "small"
                    }
                  }
                }
              ],
              "z": 20,
              "hasOpenThreats": false,
              "attrs": {
                ".marker-target": {
                  "class": "marker-target hasNoOpenThreats isInScope"
                },
                ".connection": {
                  "class": "connection hasNoOpenThreats isInScope"
                }
              }
            },
            {
              "type": "tm.Process",
              "size": {
                "width": 100,
                "height": 100
              },
              "position": {
                "x": 1117,
                "y": 290
              },
              "angle": 0,
              "id": "35f8d852-1e8b-4af3-abfa-8e98d853d680",
              "z": 21,
              "hasOpenThreats": false,
              "attrs": {
                ".element-shape": {
                  "class": "element-shape hasNoOpenThreats isInScope"
                },
                "text": {
                  "text": "Paypal &\nSTRIPE APIs"
                },
                ".element-text": {
                  "class": "element-text hasNoOpenThreats isInScope"
                }
              }
            },
            {
              "type": "tm.Flow",
              "smooth": true,
              "source": {
                "id": "35f8d852-1e8b-4af3-abfa-8e98d853d680"
              },
              "target": {
                "id": "8aa6e2f9-ea6a-4cc2-b8f6-2997c8c2b125"
              },
              "vertices": [
                {
                  "x": 989,
                  "y": 303
                }
              ],
              "id": "aa6f8c8e-3957-436c-8fbf-df33782fc52e",
              "labels": [
                {
                  "position": {
                    "distance": 0.5367521449599725,
                    "offset": 15.097705673351705
                  },
                  "attrs": {
                    "text": {
                      "text": "API Response",
                      "font-weight": "400",
                      "font-size": "small"
                    }
                  }
                }
              ],
              "z": 23,
              "hasOpenThreats": false,
              "attrs": {
                ".marker-target": {
                  "class": "marker-target hasNoOpenThreats isInScope"
                },
                ".connection": {
                  "class": "connection hasNoOpenThreats isInScope"
                }
              }
            },
            {
              "type": "tm.Flow",
              "smooth": true,
              "source": {
                "id": "8aa6e2f9-ea6a-4cc2-b8f6-2997c8c2b125"
              },
              "target": {
                "id": "35f8d852-1e8b-4af3-abfa-8e98d853d680"
              },
              "vertices": [
                {
                  "x": 1003,
                  "y": 372
                }
              ],
              "id": "1c328a60-d15b-4e67-b14a-b57333686fbb",
              "labels": [
                {
                  "position": 0.5,
                  "attrs": {
                    "text": {
                      "text": "API Request",
                      "font-weight": "400",
                      "font-size": "small"
                    }
                  }
                }
              ],
              "z": 24,
              "hasOpenThreats": false,
              "attrs": {
                ".marker-target": {
                  "class": "marker-target hasNoOpenThreats isInScope"
                },
                ".connection": {
                  "class": "connection hasNoOpenThreats isInScope"
                }
              }
            },
            {
              "type": "tm.Flow",
              "smooth": true,
              "source": {
                "x": 1457,
                "y": 345
              },
              "target": {
                "id": "35f8d852-1e8b-4af3-abfa-8e98d853d680"
              },
              "vertices": [
                {
                  "x": 1330,
                  "y": 374
                }
              ],
              "id": "8af2f1b0-f800-49d7-a845-b4ad6adebf83",
              "labels": [
                {
                  "position": {
                    "distance": 0.5285053679895745,
                    "offset": -21.998281451389794
                  },
                  "attrs": {
                    "text": {
                      "text": "Payment Response",
                      "font-weight": "400",
                      "font-size": "small"
                    }
                  }
                }
              ],
              "z": 26,
              "hasOpenThreats": false,
              "attrs": {
                ".marker-target": {
                  "class": "marker-target hasNoOpenThreats isInScope"
                },
                ".connection": {
                  "class": "connection hasNoOpenThreats isInScope"
                }
              }
            },
            {
              "type": "tm.Process",
              "size": {
                "width": 100,
                "height": 100
              },
              "position": {
                "x": 549,
                "y": 214
              },
              "angle": 0,
              "id": "d5424603-0c19-40a4-82f4-04cd0f1f5388",
              "z": 27,
              "hasOpenThreats": false,
              "attrs": {
                ".element-shape": {
                  "class": "element-shape hasNoOpenThreats isInScope"
                },
                "text": {
                  "text": "Load Balancer"
                },
                ".element-text": {
                  "class": "element-text hasNoOpenThreats isInScope"
                }
              }
            },
            {
              "type": "tm.Flow",
              "smooth": true,
              "source": {
                "id": "d5424603-0c19-40a4-82f4-04cd0f1f5388"
              },
              "target": {
                "id": "8aa6e2f9-ea6a-4cc2-b8f6-2997c8c2b125"
              },
              "vertices": [
                {
                  "x": 698,
                  "y": 297
                }
              ],
              "id": "486dd091-3e97-4b5e-830b-ad08acea793c",
              "labels": [
                {
                  "position": {
                    "distance": 0.43139205959585014,
                    "offset": -16.350433935007864
                  },
                  "attrs": {
                    "text": {
                      "text": "flow 27",
                      "font-weight": "400",
                      "font-size": "small"
                    }
                  }
                }
              ],
              "z": 28,
              "hasOpenThreats": false,
              "attrs": {
                ".marker-target": {
                  "class": "marker-target hasNoOpenThreats isInScope"
                },
                ".connection": {
                  "class": "connection hasNoOpenThreats isInScope"
                }
              }
            },
            {
              "type": "tm.Flow",
              "smooth": true,
              "source": {
                "id": "8aa6e2f9-ea6a-4cc2-b8f6-2997c8c2b125"
              },
              "target": {
                "id": "d5424603-0c19-40a4-82f4-04cd0f1f5388"
              },
              "vertices": [
                {
                  "x": 688,
                  "y": 361
                }
              ],
              "id": "a1dde39a-93e2-4f0e-ba7c-ee9b51a0c254",
              "labels": [
                {
                  "position": 0.5,
                  "attrs": {
                    "text": {
                      "text": "flow 28",
                      "font-weight": "400",
                      "font-size": "small"
                    }
                  }
                }
              ],
              "z": 29,
              "hasOpenThreats": false,
              "attrs": {
                ".marker-target": {
                  "class": "marker-target hasNoOpenThreats isInScope"
                },
                ".connection": {
                  "class": "connection hasNoOpenThreats isInScope"
                }
              }
            },
            {
              "type": "tm.Actor",
              "size": {
                "width": 160,
                "height": 80
              },
              "position": {
                "x": 995,
                "y": 1
              },
              "angle": 0,
              "id": "8070903d-4e3b-430b-a600-0ef37acddb39",
              "z": 30,
              "hasOpenThreats": false,
              "attrs": {
                ".element-shape": {
                  "class": "element-shape hasNoOpenThreats isInScope"
                },
                "text": {
                  "text": "Google Analytics"
                },
                ".element-text": {
                  "class": "element-text hasNoOpenThreats isInScope"
                }
              }
            },
            {
              "type": "tm.Flow",
              "smooth": true,
              "source": {
                "id": "8aa6e2f9-ea6a-4cc2-b8f6-2997c8c2b125"
              },
              "target": {
                "id": "8070903d-4e3b-430b-a600-0ef37acddb39"
              },
              "vertices": [
                {
                  "x": 947,
                  "y": 157
                }
              ],
              "id": "5746063f-8222-462d-81db-b5cfceeef499",
              "labels": [
                {
                  "position": 0.5,
                  "attrs": {
                    "text": {
                      "text": "flow 30",
                      "font-weight": "400",
                      "font-size": "small"
                    }
                  }
                }
              ],
              "z": 31,
              "hasOpenThreats": false,
              "attrs": {
                ".marker-target": {
                  "class": "marker-target hasNoOpenThreats isInScope"
                },
                ".connection": {
                  "class": "connection hasNoOpenThreats isInScope"
                }
              }
            },
            {
              "type": "tm.Flow",
              "smooth": true,
              "source": {
                "id": "8070903d-4e3b-430b-a600-0ef37acddb39"
              },
              "target": {
                "id": "8aa6e2f9-ea6a-4cc2-b8f6-2997c8c2b125"
              },
              "vertices": [
                {
                  "x": 1020,
                  "y": 164
                }
              ],
              "id": "245edf0d-5a19-4ae9-b965-f50f9d441897",
              "labels": [
                {
                  "position": 0.5,
                  "attrs": {
                    "text": {
                      "text": "flow 31",
                      "font-weight": "400",
                      "font-size": "small"
                    }
                  }
                }
              ],
              "z": 32,
              "hasOpenThreats": false,
              "attrs": {
                ".marker-target": {
                  "class": "marker-target hasNoOpenThreats isInScope"
                },
                ".connection": {
                  "class": "connection hasNoOpenThreats isInScope"
                }
              }
            },
            {
              "type": "tm.Process",
              "size": {
                "width": 100,
                "height": 100
              },
              "position": {
                "x": 1020,
                "y": 1030
              },
              "angle": 0,
              "id": "296d1859-6379-4a38-925e-98547c53f2da",
              "z": 33,
              "hasOpenThreats": false,
              "attrs": {
                ".element-shape": {
                  "class": "element-shape hasNoOpenThreats isInScope"
                },
                "text": {
                  "text": "Data Backup\nEncryption"
                },
                ".element-text": {
                  "class": "element-text hasNoOpenThreats isInScope"
                }
              }
            },
            {
              "type": "tm.Store",
              "size": {
                "width": 160,
                "height": 80
              },
              "position": {
                "x": 1209,
                "y": 786
              },
              "angle": 0,
              "id": "aeb98425-a36d-42bc-a63f-8060ddc5792b",
              "z": 34,
              "hasOpenThreats": false,
              "attrs": {
                ".element-shape": {
                  "class": "element-shape hasNoOpenThreats isInScope"
                },
                "text": {
                  "text": "Data Storage Device in\nSecondary Data Centre"
                },
                ".element-text": {
                  "class": "element-text hasNoOpenThreats isInScope"
                }
              }
            },
            {
              "type": "tm.Store",
              "size": {
                "width": 160,
                "height": 80
              },
              "position": {
                "x": 1132,
                "y": 1173
              },
              "angle": 0,
              "id": "1a4cc806-e74b-45dc-8eb9-422d88ae21db",
              "z": 35,
              "hasOpenThreats": false,
              "attrs": {
                ".element-shape": {
                  "class": "element-shape hasNoOpenThreats isInScope"
                },
                "text": {
                  "text": "Cloud Storage Service\n(by External Supplier)"
                },
                ".element-text": {
                  "class": "element-text hasNoOpenThreats isInScope"
                }
              }
            },
            {
              "type": "tm.Flow",
              "smooth": true,
              "source": {
                "x": 430,
                "y": 808
              },
              "target": {
                "id": "d5358155-20c4-42b0-b202-7aa9fe71c391"
              },
              "vertices": [
                {
                  "x": 610,
                  "y": 742
                }
              ],
              "id": "7d796342-369e-452f-b0cf-341f8edb95ed",
              "labels": [
                {
                  "position": 0.5,
                  "attrs": {
                    "text": {
                      "text": "flow 36",
                      "font-weight": "400",
                      "font-size": "small"
                    }
                  }
                }
              ],
              "z": 37,
              "hasOpenThreats": false,
              "attrs": {
                ".marker-target": {
                  "class": "marker-target hasNoOpenThreats isInScope"
                },
                ".connection": {
                  "class": "connection hasNoOpenThreats isInScope"
                }
              }
            },
            {
              "type": "tm.Flow",
              "smooth": true,
              "source": {
                "id": "d5358155-20c4-42b0-b202-7aa9fe71c391"
              },
              "target": {
                "x": 405,
                "y": 788
              },
              "vertices": [
                {
                  "x": 566,
                  "y": 671
                }
              ],
              "id": "2999cba1-5b32-4f1d-93e1-bfd8b892e0ca",
              "labels": [
                {
                  "position": {
                    "distance": 0.616843321741467,
                    "offset": 20.967391869200636
                  },
                  "attrs": {
                    "text": {
                      "text": "flow 37",
                      "font-weight": "400",
                      "font-size": "small"
                    }
                  }
                }
              ],
              "z": 38,
              "hasOpenThreats": false,
              "attrs": {
                ".marker-target": {
                  "class": "marker-target hasNoOpenThreats isInScope"
                },
                ".connection": {
                  "class": "connection hasNoOpenThreats isInScope"
                }
              }
            },
            {
              "type": "tm.Process",
              "size": {
                "width": 100,
                "height": 100
              },
              "position": {
                "x": 286,
                "y": 550
              },
              "angle": 0,
              "id": "62a22af8-860f-44ba-9590-fecb75daa01e",
              "z": 39,
              "hasOpenThreats": false,
              "attrs": {
                ".element-shape": {
                  "class": "element-shape hasNoOpenThreats isInScope"
                },
                "text": {
                  "text": "VPN"
                },
                ".element-text": {
                  "class": "element-text hasNoOpenThreats isInScope"
                }
              }
            },
            {
              "type": "tm.Actor",
              "size": {
                "width": 160,
                "height": 80
              },
              "position": {
                "x": 1459,
                "y": 290
              },
              "angle": 0,
              "id": "0ea25e9e-0a13-49d3-8a53-a5754dd5b566",
              "z": 41,
              "hasOpenThreats": false,
              "attrs": {
                ".element-shape": {
                  "class": "element-shape hasNoOpenThreats isInScope"
                },
                "text": {
                  "text": "Payment Processing"
                },
                ".element-text": {
                  "class": "element-text hasNoOpenThreats isInScope"
                }
              }
            },
            {
              "type": "tm.Flow",
              "smooth": true,
              "source": {
                "id": "35f8d852-1e8b-4af3-abfa-8e98d853d680"
              },
              "target": {
                "id": "0ea25e9e-0a13-49d3-8a53-a5754dd5b566"
              },
              "vertices": [
                {
                  "x": 1336,
                  "y": 287
                }
              ],
              "id": "2f0af20f-6817-42cc-acea-6fa4a0651f58",
              "labels": [
                {
                  "position": {
                    "distance": 0.5102173480116533,
                    "offset": -13.947661576317534
                  },
                  "attrs": {
                    "text": {
                      "text": "Payment Request",
                      "font-weight": "400",
                      "font-size": "small"
                    }
                  }
                }
              ],
              "z": 42,
              "hasOpenThreats": false,
              "attrs": {
                ".marker-target": {
                  "class": "marker-target hasNoOpenThreats isInScope"
                },
                ".connection": {
                  "class": "connection hasNoOpenThreats isInScope"
                }
              }
            },
            {
              "type": "tm.Process",
              "size": {
                "width": 100,
                "height": 100
              },
              "position": {
                "x": 336,
                "y": 789
              },
              "angle": 0,
              "id": "ac2c21a4-109a-4363-afe5-37392075caa2",
              "z": 43,
              "hasOpenThreats": false,
              "attrs": {
                ".element-shape": {
                  "class": "element-shape hasNoOpenThreats isInScope"
                },
                "text": {
                  "text": "SNS API"
                },
                ".element-text": {
                  "class": "element-text hasNoOpenThreats isInScope"
                }
              }
            },
            {
              "type": "tm.Flow",
              "smooth": true,
              "source": {
                "id": "5eb0c940-6b7d-43af-b15b-47965536b7cd"
              },
              "target": {
                "id": "296d1859-6379-4a38-925e-98547c53f2da"
              },
              "vertices": [
                {
                  "x": 917,
                  "y": 983
                }
              ],
              "id": "22bb714c-11db-42d1-84ef-1e99d4c485ad",
              "labels": [
                {
                  "position": 0.5,
                  "attrs": {
                    "text": {
                      "text": "Database Copy",
                      "font-weight": "400",
                      "font-size": "small"
                    }
                  }
                }
              ],
              "z": 44,
              "hasOpenThreats": false,
              "attrs": {
                ".marker-target": {
                  "class": "marker-target hasNoOpenThreats isInScope"
                },
                ".connection": {
                  "class": "connection hasNoOpenThreats isInScope"
                }
              }
            },
            {
              "type": "tm.Flow",
              "smooth": true,
              "source": {
                "id": "296d1859-6379-4a38-925e-98547c53f2da"
              },
              "target": {
                "id": "5eb0c940-6b7d-43af-b15b-47965536b7cd"
              },
              "vertices": [],
              "id": "7b74deb8-6829-4ef1-b655-71ffd57cd0ba",
              "labels": [
                {
                  "position": 0.5,
                  "attrs": {
                    "text": {
                      "text": "flow 41",
                      "font-weight": "400",
                      "font-size": "small"
                    }
                  }
                }
              ],
              "z": 45,
              "hasOpenThreats": false,
              "attrs": {
                ".marker-target": {
                  "class": "marker-target hasNoOpenThreats isInScope"
                },
                ".connection": {
                  "class": "connection hasNoOpenThreats isInScope"
                }
              }
            },
            {
              "type": "tm.Actor",
              "size": {
                "width": 160,
                "height": 80
              },
              "position": {
                "x": 939,
                "y": 1180
              },
              "angle": 0,
              "id": "34be5a56-7f1c-42f4-a9a3-0580c9d7eeb2",
              "z": 46,
              "hasOpenThreats": false,
              "attrs": {
                ".element-shape": {
                  "class": "element-shape hasNoOpenThreats isInScope"
                },
                "text": {
                  "text": "Cloud Storage Service\n(by External Supplier)"
                },
                ".element-text": {
                  "class": "element-text hasNoOpenThreats isInScope"
                }
              }
            },
            {
              "type": "tm.Flow",
              "smooth": true,
              "source": {
                "id": "5eb0c940-6b7d-43af-b15b-47965536b7cd"
              },
              "target": {
                "id": "aeb98425-a36d-42bc-a63f-8060ddc5792b"
              },
              "vertices": [
                {
                  "x": 1022,
                  "y": 831
                }
              ],
              "id": "6129787c-6e5b-49dc-a9fb-491c503e6134",
              "labels": [
                {
                  "position": 0.5,
                  "attrs": {
                    "text": {
                      "text": "Database Copy",
                      "font-weight": "400",
                      "font-size": "small"
                    }
                  }
                }
              ],
              "z": 47,
              "hasOpenThreats": false,
              "attrs": {
                ".marker-target": {
                  "class": "marker-target hasNoOpenThreats isInScope"
                },
                ".connection": {
                  "class": "connection hasNoOpenThreats isInScope"
                }
              }
            },
            {
              "type": "tm.Flow",
              "smooth": true,
              "source": {
                "id": "aeb98425-a36d-42bc-a63f-8060ddc5792b"
              },
              "target": {
                "id": "5eb0c940-6b7d-43af-b15b-47965536b7cd"
              },
              "vertices": [
                {
                  "x": 1031,
                  "y": 914
                }
              ],
              "id": "6e980c02-13c4-4655-8e5c-ef2df0d7456a",
              "labels": [
                {
                  "position": {
                    "distance": 0.45664296811344257,
                    "offset": -32.730582607241196
                  },
                  "attrs": {
                    "text": {
                      "text": "flow 44",
                      "font-weight": "400",
                      "font-size": "small"
                    }
                  }
                }
              ],
              "z": 48,
              "hasOpenThreats": false,
              "attrs": {
                ".marker-target": {
                  "class": "marker-target hasNoOpenThreats isInScope"
                },
                ".connection": {
                  "class": "connection hasNoOpenThreats isInScope"
                }
              }
            },
            {
              "type": "tm.Flow",
              "smooth": true,
              "source": {
                "id": "d5358155-20c4-42b0-b202-7aa9fe71c391"
              },
              "target": {
                "id": "62a22af8-860f-44ba-9590-fecb75daa01e"
              },
              "vertices": [
                {
                  "x": 481,
                  "y": 556
                }
              ],
              "id": "f22037e3-d176-48cf-a789-67261ae5dd32",
              "labels": [
                {
                  "position": {
                    "distance": 0.5143087617014104,
                    "offset": 2.719579161224919
                  },
                  "attrs": {
                    "text": {
                      "text": "flow 45",
                      "font-weight": "400",
                      "font-size": "small"
                    }
                  }
                }
              ],
              "z": 49,
              "hasOpenThreats": false,
              "attrs": {
                ".marker-target": {
                  "class": "marker-target hasNoOpenThreats isInScope"
                },
                ".connection": {
                  "class": "connection hasNoOpenThreats isInScope"
                }
              }
            },
            {
              "type": "tm.Flow",
              "smooth": true,
              "source": {
                "id": "62a22af8-860f-44ba-9590-fecb75daa01e"
              },
              "target": {
                "id": "d5358155-20c4-42b0-b202-7aa9fe71c391"
              },
              "vertices": [],
              "id": "10d099c4-d1db-419a-a16c-c71e051ee57e",
              "labels": [
                {
                  "position": 0.5,
                  "attrs": {
                    "text": {
                      "text": "flow 46",
                      "font-weight": "400",
                      "font-size": "small"
                    }
                  }
                }
              ],
              "z": 50,
              "hasOpenThreats": false,
              "attrs": {
                ".marker-target": {
                  "class": "marker-target hasNoOpenThreats isInScope"
                },
                ".connection": {
                  "class": "connection hasNoOpenThreats isInScope"
                }
              }
            },
            {
              "type": "tm.Process",
              "size": {
                "width": 100,
                "height": 100
              },
              "position": {
                "x": 765,
                "y": 1
              },
              "angle": 0,
              "id": "faff9e52-4a8f-415d-b629-4e8169855642",
              "z": 53,
              "hasOpenThreats": false,
              "attrs": {
                ".element-shape": {
                  "class": "element-shape hasNoOpenThreats isInScope"
                },
                "text": {
                  "text": "One Signal\nREST API"
                },
                ".element-text": {
                  "class": "element-text hasNoOpenThreats isInScope"
                }
              }
            },
            {
              "type": "tm.Actor",
              "size": {
                "width": 160,
                "height": 80
              },
              "position": {
                "x": 9,
                "y": 568
              },
              "angle": 0,
              "id": "18828d41-8efa-4df0-9541-481df76aa9ab",
              "z": 54,
              "hasOpenThreats": false,
              "attrs": {
                ".element-shape": {
                  "class": "element-shape hasNoOpenThreats isInScope"
                },
                "text": {
                  "text": "Telecoms Operator's API"
                },
                ".element-text": {
                  "class": "element-text hasNoOpenThreats isInScope"
                }
              }
            },
            {
              "type": "tm.Flow",
              "smooth": true,
              "source": {
                "id": "18828d41-8efa-4df0-9541-481df76aa9ab"
              },
              "target": {
                "id": "62a22af8-860f-44ba-9590-fecb75daa01e"
              },
              "vertices": [
                {
                  "x": 229,
                  "y": 552
                }
              ],
              "id": "67f77771-45e1-479a-864d-bd85cab3f4ce",
              "labels": [
                {
                  "position": 0.5,
                  "attrs": {
                    "text": {
                      "text": "flow 48",
                      "font-weight": "400",
                      "font-size": "small"
                    }
                  }
                }
              ],
              "z": 55,
              "attrs": {}
            },
            {
              "type": "tm.Flow",
              "smooth": true,
              "source": {
                "x": 286,
                "y": 616
              },
              "target": {
                "id": "18828d41-8efa-4df0-9541-481df76aa9ab"
              },
              "vertices": [],
              "id": "044e0f3d-48a0-4994-a92c-70fc90f54fa1",
              "labels": [
                {
                  "position": 0.5,
                  "attrs": {
                    "text": {
                      "text": "flow 49",
                      "font-weight": "400",
                      "font-size": "small"
                    }
                  }
                }
              ],
              "z": 56,
              "attrs": {}
            }
          ]
        },
        "size": {
          "height": 1114.2938232421875,
          "width": 1273.7420654296875
        }
      }
    ]
  }
}